BatchExpLaunch/__init__.py
BatchExpLaunch/results_org.py
BatchExpLaunch/tools.py
BatchExpLaunch-0.0.7.data/scripts/Extract_result
BatchExpLaunch-0.0.7.data/scripts/slurmSingle
BatchExpLaunch-0.0.7.data/scripts/slurm_python
BatchExpLaunch-0.0.7.dist-info/LICENSE
BatchExpLaunch-0.0.7.dist-info/METADATA
BatchExpLaunch-0.0.7.dist-info/WHEEL
BatchExpLaunch-0.0.7.dist-info/top_level.txt
BatchExpLaunch-0.0.7.dist-info/RECORD
