Metadata-Version: 2.1
Name: BatchExpLaunch
Version: 0.0.7
Summary: A project for batch scripts submission
Home-page: https://github.com/Taosheng-ty/BEL.git
Author: Tao Yang
Author-email: taoyang@cs.utah.edu
Project-URL: Bug Tracker, https://github.com/Taosheng-ty/BEL/issues
Classifier: Programming Language :: Python :: 3
Classifier: License :: OSI Approved :: MIT License
Classifier: Operating System :: OS Independent
Requires-Python: >=3.0
License-File: LICENSE
